django_doc/__init__.py
django_doc/main.py
django_doc/management/__init__.py
django_doc/management/commands/__init__.py
django_doc/management/commands/collectdoc.py
django_doc-1.1.dist-info/METADATA
django_doc-1.1.dist-info/WHEEL
django_doc-1.1.dist-info/top_level.txt
django_doc-1.1.dist-info/RECORD
